src/__init__.py
src/bootstrap.py
src/main.py
talos_audit_service-1.1.1.dist-info/METADATA
talos_audit_service-1.1.1.dist-info/WHEEL
talos_audit_service-1.1.1.dist-info/top_level.txt
talos_audit_service-1.1.1.dist-info/RECORD
