Metadata-Version: 2.4
Name: talos-audit-service
Version: 1.1.1
Summary: Talos Protocol Audit Log Service
Requires-Python: >=3.10
Requires-Dist: fastapi
Requires-Dist: uvicorn
Requires-Dist: sqlalchemy
Requires-Dist: alembic
Provides-Extra: dev
Requires-Dist: ruff; extra == "dev"
Requires-Dist: pytest; extra == "dev"
Requires-Dist: pytest-cov; extra == "dev"
Requires-Dist: httpx; extra == "dev"
Requires-Dist: uvicorn; extra == "dev"
